MANIFEST.in
README.md
setup.py
django_fakeimg.egg-info/PKG-INFO
django_fakeimg.egg-info/SOURCES.txt
django_fakeimg.egg-info/dependency_links.txt
django_fakeimg.egg-info/not-zip-safe
django_fakeimg.egg-info/requires.txt
django_fakeimg.egg-info/top_level.txt
fakeimg/__init__.py
fakeimg/models.py
fakeimg/urls.py
fakeimg/views.py
fakeimg/font/.DS_Store
fakeimg/font/bebas.otf
fakeimg/font/lobster.otf
fakeimg/font/museo.otf
fakeimg/font/yanone.otf