Metadata-Version: 1.1
Name: django-fakeimg
Version: 0.1.2
Summary: A django port of fakeimg.pl
Home-page: http://github.com/scao/django-fakeimg
Author: Shu Cao
Author-email: shucao@gmail.com
License: BSD
Platform: UNKNOWN
Classifier: Development Status :: 4 - Beta
Classifier: Environment :: Web Environment
Classifier: Intended Audience :: Developers
Classifier: License :: OSI Approved :: BSD License
Classifier: Operating System :: OS Independent
Classifier: Programming Language :: Python
Classifier: Framework :: Django
